punch_clock/__init__.py
punch_clock/punch_clock.py
punch_clock/utils.py
punch_clock-0.1.2.dist-info/METADATA
punch_clock-0.1.2.dist-info/WHEEL
punch_clock-0.1.2.dist-info/RECORD
